[
    { "date": "2024-03-01", "description": "Started Working as a TA for CSE 224." },
    { "date": "2023-09-01", "description": "Started Working as a TA for CSE 107." },
    { "date": "2023-07-01", "description": "Started Working at UCSD Health as Research Intern at Bazhlab UCSD." },
    { "date": "2023-01-01", "description": "Started Working as a Researcher in Cryptography at Prof. Nadia Heninger’s Lab." },
    { "date": "2022-09-14", "description": "Started Master’s in Computer Science at UCSD." },
    { "date": "2022-06-11", "description": "Completed Bachelor’s in Computer Engineering." },
    { "date": "2021-01-01", "description": "Started Working at XinFin Network Part Time." },
    { "date": "2020-09-01", "description": "Started Research at PICT Lab, working on Dehazing Images." },
    { "date": "2020-07-11", "description": "Joined my first Internship at Zubi Infotech Pvt. Ltd." },
    { "date": "2018-06-11", "description": "Started my Bachelor’s in Computer Engineering at Pune Institute of Computer Engineering." }
  ]
  